{"nodes": [{"id": "header", "label": "Header.jsx", "file_type": "code", "source_file": "src\\Components\\Shared\\Header\\Header.jsx", "source_location": "L1"}, {"id": "header_header", "label": "Header()", "file_type": "code", "source_file": "src\\Components\\Shared\\Header\\Header.jsx", "source_location": "L8"}], "edges": [{"source": "header", "target": "react", "relation": "imports_from", "confidence": "EXTRACTED", "source_file": "src\\Components\\Shared\\Header\\Header.jsx", "source_location": "L2", "weight": 1.0}, {"source": "header", "target": "randerheader", "relation": "imports_from", "confidence": "EXTRACTED", "source_file": "src\\Components\\Shared\\Header\\Header.jsx", "source_location": "L3", "weight": 1.0}, {"source": "header", "target": "banner", "relation": "imports_from", "confidence": "EXTRACTED", "source_file": "src\\Components\\Shared\\Header\\Header.jsx", "source_location": "L4", "weight": 1.0}, {"source": "header", "target": "navigation", "relation": "imports_from", "confidence": "EXTRACTED", "source_file": "src\\Components\\Shared\\Header\\Header.jsx", "source_location": "L5", "weight": 1.0}, {"source": "header", "target": "next_intl", "relation": "imports_from", "confidence": "EXTRACTED", "source_file": "src\\Components\\Shared\\Header\\Header.jsx", "source_location": "L6", "weight": 1.0}, {"source": "header", "target": "header_header", "relation": "contains", "confidence": "EXTRACTED", "source_file": "src\\Components\\Shared\\Header\\Header.jsx", "source_location": "L8", "weight": 1.0}]}